automate_teaching/__init__.py
automate_teaching/exam.py
automate_teaching/google.py
automate_teaching/latex.py
automate_teaching-0.0.8.dist-info/licenses/LICENSE
automate_teaching-0.0.8.dist-info/METADATA
automate_teaching-0.0.8.dist-info/WHEEL
automate_teaching-0.0.8.dist-info/top_level.txt
automate_teaching-0.0.8.dist-info/RECORD
